LICENSE
MANIFEST.in
README.md
setup.py
cbpi4_SimulatedSensor/__init__.py
cbpi4_SimulatedSensor/config.yaml
cbpi4_SimulatedSensor.egg-info/PKG-INFO
cbpi4_SimulatedSensor.egg-info/SOURCES.txt
cbpi4_SimulatedSensor.egg-info/dependency_links.txt
cbpi4_SimulatedSensor.egg-info/top_level.txt
cbpi4_SimulatedSensor/static/cbpi.png
cbpi4_SimulatedSensor/static/index.html
cbpi4_SimulatedSensor/static/style.css