Metadata-Version: 2.1
Name: cbpi4-SimulatedSensor
Version: 0.0.2
Summary: This plugin allowes you to simulate a sensor. The sensor will check if a Kettle is currently heating and will increase its value by a configurable amount. If the Kettle is not heating the temperature will be decreased by a configurable amount.
Home-page: https://pypi.org/project/cbpi4-SimulatedSensor/
Author: prash3r
Author-email: pypi@prash3r.de
License: UNKNOWN
Platform: UNKNOWN
License-File: LICENSE
